lnkgonewild/LICENSE
lnkgonewild/README.MD
lnkgonewild/__init__.py
lnkgonewild/lnkcompile.py
lnkgonewild/requirements.txt
lnkgonewild/secretsubprocess.py
lnkgonewild/thirdparty.json
lnkgonewild-0.10.dist-info/LICENSE.rst
lnkgonewild-0.10.dist-info/METADATA
lnkgonewild-0.10.dist-info/WHEEL
lnkgonewild-0.10.dist-info/top_level.txt
lnkgonewild-0.10.dist-info/RECORD
