Metadata-Version: 2.1
Name: lnkgonewild
Version: 0.10
Summary: Creates .lnk files (with admin rights if desired), can execute any file in hidden mode (no more bothersome popups when executing .bat/.cmd files)
Home-page: https://github.com/hansalemaos/lnkgonewild
Author: Johannes Fischer
Author-email: <aulasparticularesdealemaosp@gmail.com>
License: MIT
Keywords: hidden,subprocess,windows,lnk,links,shortcuts
Classifier: Development Status :: 4 - Beta
Classifier: Programming Language :: Python :: 3 :: Only
Classifier: Programming Language :: Python :: 3.10
Classifier: Topic :: Scientific/Engineering :: Visualization
Classifier: Topic :: Software Development :: Libraries :: Python Modules
Classifier: Topic :: Utilities
License-File: LICENSE.rst
Requires-Dist: nutikacompile
